dstools/FrozenJSON.py
dstools/__init__.py
dstools/cli.py
dstools/env.py
dstools/exceptions.py
dstools/path.py
dstools/repo.py
dstools/testing.py
dstools/util.py
dstools/env/__init__.py
dstools/env/env.py
dstools/params/__init__.py
dstools/params/grid.py
dstools/pg/__init__.py
dstools/pg/introspection.py
dstools/pg/schema.py
dstools/pg/util.py
dstools/pipeline/Client.py
dstools/pipeline/CodeDiffer.py
dstools/pipeline/Table.py
dstools/pipeline/__init__.py
dstools/pipeline/build_report.py
dstools/pipeline/clients.py
dstools/pipeline/constants.py
dstools/pipeline/dag.py
dstools/pipeline/exceptions.py
dstools/pipeline/executors.py
dstools/pipeline/helpers.py
dstools/pipeline/io.py
dstools/pipeline/notifications.py
dstools/pipeline/postgres.py
dstools/pipeline/products.py
dstools/pipeline/tasks.py
dstools/pipeline/util.py
dstools/pipeline/clients/Client.py
dstools/pipeline/clients/__init__.py
dstools/pipeline/clients/db.py
dstools/pipeline/clients/shell.py
dstools/pipeline/executors/Executor.py
dstools/pipeline/executors/LoggerHandler.py
dstools/pipeline/executors/Parallel.py
dstools/pipeline/executors/Serial.py
dstools/pipeline/executors/__init__.py
dstools/pipeline/placeholders/__init__.py
dstools/pipeline/placeholders/placeholders.py
dstools/pipeline/products/File.py
dstools/pipeline/products/GenericProduct.py
dstools/pipeline/products/MetaProduct.py
dstools/pipeline/products/Product.py
dstools/pipeline/products/__init__.py
dstools/pipeline/products/products.py
dstools/pipeline/products/serializers.py
dstools/pipeline/products/sql.py
dstools/pipeline/resources/__init__.py
dstools/pipeline/resources/dag.md
dstools/pipeline/resources/github-markdown.html
dstools/pipeline/sources/__init__.py
dstools/pipeline/sources/sources.py
dstools/pipeline/sql/__init__.py
dstools/pipeline/sql/enum.py
dstools/pipeline/sql/products.py
dstools/pipeline/sql/tasks.py
dstools/pipeline/sql/pg/__init__.py
dstools/pipeline/tasks/Params.py
dstools/pipeline/tasks/Task.py
dstools-0.27.dist-info/LICENSE
dstools-0.27.dist-info/METADATA
dstools-0.27.dist-info/WHEEL
dstools-0.27.dist-info/entry_points.txt
dstools-0.27.dist-info/top_level.txt
dstools-0.27.dist-info/RECORD
